dockerblade/__init__.py
dockerblade/container.py
dockerblade/daemon.py
dockerblade/exceptions.py
dockerblade/files.py
dockerblade/popen.py
dockerblade/py.typed
dockerblade/shell.py
dockerblade/stopwatch.py
dockerblade/util.py
dockerblade/version.py
dockerblade-0.6.2.dist-info/LICENSE
dockerblade-0.6.2.dist-info/METADATA
dockerblade-0.6.2.dist-info/WHEEL
dockerblade-0.6.2.dist-info/RECORD
