Metadata-Version: 2.1
Name: dockerblade
Version: 0.6.2
Summary: Interact with Docker containers via Python-like APIs
Home-page: https://github.com/ChrisTimperley/dockerblade
License: Apache-2.0
Author: Chris Timperley
Author-email: ctimperley@cmu.edu
Requires-Python: >=3.11,<4
Classifier: Intended Audience :: Developers
Classifier: License :: OSI Approved :: Apache Software License
Classifier: Programming Language :: Python :: 3
Classifier: Programming Language :: Python :: 3.11
Classifier: Programming Language :: Python :: 3.12
Classifier: Programming Language :: Python :: 3.10
Classifier: Programming Language :: Python :: 3.9
Requires-Dist: attrs (>=19.2.0)
Requires-Dist: docker (>=7.0,<8.0)
Requires-Dist: loguru (>=0.5)
Requires-Dist: mslex (>=1.2,<2.0)
Requires-Dist: psutil (>=5.7,<6.0)
Requires-Dist: requests (==2.31.0)
Project-URL: Repository, https://github.com/ChrisTimperley/dockerblade
